serialmsgpacketizer/__init__.py
serialmsgpacketizer/console.py
serialmsgpacketizer/defaultconfig.py
serialmsgpacketizer/py.typed
serialmsgpacketizer/service.py
serialmsgpacketizer-0.3.1.dist-info/entry_points.txt
serialmsgpacketizer-0.3.1.dist-info/LICENSE
serialmsgpacketizer-0.3.1.dist-info/WHEEL
serialmsgpacketizer-0.3.1.dist-info/METADATA
serialmsgpacketizer-0.3.1.dist-info/RECORD
