Metadata-Version: 2.1
Name: serialmsgpacketizer
Version: 0.3.1
Summary: Send & Receive MsgPacketizer packets over serial link
Home-page: https://gitlab.com/advian-oss/python-serialmsgpacketizer/
License: MIT
Author: Eero af Heurlin
Author-email: eero.afheurlin@iki.fi
Requires-Python: >=3.7,<4.0
Classifier: License :: OSI Approved :: MIT License
Classifier: Programming Language :: Python :: 3
Classifier: Programming Language :: Python :: 3.7
Classifier: Programming Language :: Python :: 3.8
Classifier: Programming Language :: Python :: 3.9
Requires-Dist: datastreamservicelib (>=1.8.0,<2.0.0)
Requires-Dist: msgpacketizer (>=0.2,<0.3)
Requires-Dist: pyserial (>=3.5,<4.0)
Project-URL: Repository, https://gitlab.com/advian-oss/python-serialmsgpacketizer/
